func_test/__init__.py
func_test/cache.py
func_test/lib.py
func_tests-0.0.1.dist-info/METADATA
func_tests-0.0.1.dist-info/WHEEL
func_tests-0.0.1.dist-info/top_level.txt
func_tests-0.0.1.dist-info/RECORD
