Metadata-Version: 2.1
Name: func-tests
Version: 0.0.1
Summary: Fast debug tools
Home-page: UNKNOWN
Author: Andrii Kovalov
Author-email: andy.kovv@gmail.com
License: UNKNOWN
Keywords: func_tests
Platform: UNKNOWN
Classifier: Natural Language :: English
Classifier: Programming Language :: Python :: 3.9
